WeCom_nodream/WeCom.py
WeCom_nodream/__init__.py
WeCom_nodream-1.0.0.dist-info/LICENSE.txt
WeCom_nodream-1.0.0.dist-info/METADATA
WeCom_nodream-1.0.0.dist-info/WHEEL
WeCom_nodream-1.0.0.dist-info/top_level.txt
WeCom_nodream-1.0.0.dist-info/RECORD
