Metadata-Version: 2.1
Name: WeCom-nodream
Version: 1.0.0
Summary: 企业微信API
Home-page: https://github.com/1802024110/WeCom_API
Author: noDream
Author-email: 1802024110@qq.com
License: Apache License
Platform: all
Classifier: License :: OSI Approved :: Apache Software License
Classifier: Operating System :: OS Independent
Classifier: Natural Language :: Chinese (Simplified)
Classifier: Programming Language :: Python :: 3
License-File: LICENSE.txt
Requires-Dist: requests
